setup.py
favssh/__init__.py
favssh/config.py
favssh/main.py
favssh.egg-info/PKG-INFO
favssh.egg-info/SOURCES.txt
favssh.egg-info/dependency_links.txt
favssh.egg-info/entry_points.txt
favssh.egg-info/top_level.txt