Metadata-Version: 1.0
Name: favssh
Version: 1.0
Summary: A command line tool to manipulate ssh config files
Home-page: https://github.com/ojii/favssh/
Author: Jonas Obrist
Author-email: ojiidotch@gmail.com
License: BSD
Platform: OS Independent
